README.md
setup.py
nba_stats/__init__.py
nba_stats.egg-info/PKG-INFO
nba_stats.egg-info/SOURCES.txt
nba_stats.egg-info/dependency_links.txt
nba_stats.egg-info/not-zip-safe
nba_stats.egg-info/requires.txt
nba_stats.egg-info/top_level.txt
nba_stats/retrieval/__init__.py
nba_stats/retrieval/players_retriever.py
nba_stats/retrieval/shotchart_retriever.py
nba_stats/retriever_factories/__init__.py
nba_stats/retriever_factories/api_retriever.py
nba_stats/retriever_factories/api_retriever_factory.py
nba_stats/tests/__init__.py
nba_stats/tests/api_retriever_test.py
nba_stats/utils/__init__.py
nba_stats/utils/constants.py