Metadata-Version: 1.0
Name: nba-stats
Version: 0.1
Summary: Package which is used for retrieving stats by NBA players.
Home-page: https://github.com/danchyy/nba_stats
Author: Daniel Bratulic
Author-email: danielbratulic@gmail.com
License: MIT
Project-URL: Source Code, https://github.com/danchyy/nba_stats
Keywords: nba stats analytics sports
Platform: UNKNOWN
